llama_index/llms/konko/__init__.py
llama_index/llms/konko/base.py
llama_index/llms/konko/utils.py
llama_index_llms_konko-0.4.1.dist-info/METADATA
llama_index_llms_konko-0.4.1.dist-info/WHEEL
llama_index_llms_konko-0.4.1.dist-info/licenses/LICENSE
llama_index_llms_konko-0.4.1.dist-info/RECORD
